pdfebook/__init__.py
pdfebook-0.1.4.dist-info/METADATA
pdfebook-0.1.4.dist-info/WHEEL
pdfebook-0.1.4.dist-info/entry_points.txt
pdfebook-0.1.4.dist-info/licenses/LICENSE
pdfebook-0.1.4.dist-info/RECORD
