Metadata-Version: 2.3
Name: pdfebook
Version: 0.1.4
Summary: A tool to produce a PDF ebook from an cover image and interior PDF
Author-email: Jacob Smullyan <smulloni@saggingmeniscus.com>
License-File: LICENSE
Requires-Python: >=3.12
Requires-Dist: click>=8.1.7
Requires-Dist: fpdf2>=2.7.9
Requires-Dist: pypdf>=4.2.0
